[
  {
    "id": "catkalteg001",
    "name": "Drinks",
    "originalName": "Kalte Getränke",
    "type": "category",
    "group": "drink",
    "link": ""
  },
  {
    "id": "catwarmeg002",
    "name": "Drinks",
    "originalName": "Warme Getränke",
    "type": "category",
    "group": "drink",
    "link": ""
  },
  {
    "id": "catalkoho003",
    "name": "Drinks",
    "originalName": "Alkoholfreie Getränke",
    "type": "category",
    "group": "drink",
    "link": ""
  },
  {
    "id": "catbiervo004",
    "name": "Draft",
    "originalName": "Bier vom Fass",
    "type": "category",
    "group": "drink",
    "link": ""
  },
  {
    "id": "catbierin005",
    "name": "Bottle",
    "originalName": "Bier in Flasche",
    "type": "category",
    "group": "drink",
    "link": ""
  },
  {
    "id": "catspezia006",
    "name": "Beer",
    "originalName": "Spezialbier",
    "type": "category",
    "group": "drink",
    "link": ""
  },
  {
    "id": "catweiwei007",
    "name": "Weiwein",
    "originalName": "Weißwein",
    "type": "category",
    "group": "drink",
    "link": ""
  },
  {
    "id": "catrotwei008",
    "name": "Wine",
    "originalName": "Rotwein",
    "type": "category",
    "group": "drink",
    "link": ""
  },
  {
    "id": "catrose009",
    "name": "Rose",
    "originalName": "Rosé",
    "type": "category",
    "group": "drink",
    "link": ""
  },
  {
    "id": "catsektap010",
    "name": "Aperitifs",
    "originalName": "Sekt & Aperitifs",
    "type": "category",
    "group": "drink",
    "link": ""
  },
  {
    "id": "catspirit011",
    "name": "Spirits",
    "originalName": "Spirituosen",
    "type": "category",
    "group": "drink",
    "link": ""
  },
  {
    "id": "catcockta012",
    "name": "Cocktails",
    "originalName": "Cocktails",
    "type": "category",
    "group": "drink",
    "link": ""
  },
  {
    "id": "catvorspe013",
    "name": "Appetizers",
    "originalName": "Vorspeisen",
    "type": "category",
    "group": "food",
    "link": ""
  },
  {
    "id": "catsalate014",
    "name": "Salads",
    "originalName": "Salate",
    "type": "category",
    "group": "food",
    "link": ""
  },
  {
    "id": "catpizza015",
    "name": "Pizza",
    "originalName": "Pizza",
    "type": "category",
    "group": "food",
    "link": ""
  },
  {
    "id": "catpasta016",
    "name": "Pasta",
    "originalName": "Pasta",
    "type": "category",
    "group": "food",
    "link": ""
  },
  {
    "id": "catfleisc017",
    "name": "Dishes",
    "originalName": "Fleischgerichte",
    "type": "category",
    "group": "food",
    "link": ""
  },
  {
    "id": "catfischg018",
    "name": "Dishes",
    "originalName": "Fischgerichte",
    "type": "category",
    "group": "food",
    "link": ""
  },
  {
    "id": "catvegeta019",
    "name": "Vegetarian",
    "originalName": "Vegetarisch",
    "type": "category",
    "group": "food",
    "link": ""
  },
  {
    "id": "catvegan020",
    "name": "Vegan",
    "originalName": "Vegan",
    "type": "category",
    "group": "food",
    "link": ""
  },
  {
    "id": "catbeilag021",
    "name": "Sides",
    "originalName": "Beilagen",
    "type": "category",
    "group": "food",
    "link": ""
  },
  {
    "id": "catdesser022",
    "name": "Desserts",
    "originalName": "Desserts",
    "type": "category",
    "group": "food",
    "link": ""
  },
  {
    "id": "catkinder023",
    "name": "Menu",
    "originalName": "Kindergerichte",
    "type": "category",
    "group": "food",
    "link": ""
  },
  {
    "id": "catvorspe024",
    "name": "Appetizers",
    "originalName": "Vorspeisen",
    "type": "category",
    "group": "other",
    "link": ""
  },
  {
    "id": "catnachsp025",
    "name": "Desserts",
    "originalName": "Nachspeisen",
    "type": "category",
    "group": "other",
    "link": ""
  },
  {
    "id": "catice026",
    "name": "Ice",
    "originalName": "Ice",
    "type": "category",
    "group": "other",
    "link": ""
  },
  {
    "id": "catcake027",
    "name": "Cake",
    "originalName": "Cake",
    "type": "category",
    "group": "other",
    "link": ""
  },
  {
    "id": "itmminera028",
    "name": "Still",
    "originalName": "Mineralwasser (still)",
    "type": "item",
    "group": "drink",
    "link": ""
  },
  {
    "id": "itmminera029",
    "name": "Sparkling",
    "originalName": "Mineralwasser (sprudelnd)",
    "type": "item",
    "group": "drink",
    "link": ""
  },
  {
    "id": "itmcola030",
    "name": "Cola",
    "originalName": "Cola",
    "type": "item",
    "group": "drink",
    "link": ""
  },
  {
    "id": "itmcolaze031",
    "name": "Zero",
    "originalName": "Cola Zero",
    "type": "item",
    "group": "drink",
    "link": ""
  },
  {
    "id": "itmfanta032",
    "name": "Fanta",
    "originalName": "Fanta",
    "type": "item",
    "group": "drink",
    "link": ""
  },
  {
    "id": "itmsprite033",
    "name": "Sprite",
    "originalName": "Sprite",
    "type": "item",
    "group": "drink",
    "link": ""
  },
  {
    "id": "itmspezi034",
    "name": "Spezi",
    "originalName": "Spezi",
    "type": "item",
    "group": "drink",
    "link": ""
  },
  {
    "id": "itmeistee035",
    "name": "Lemon",
    "originalName": "Eistee Zitrone",
    "type": "item",
    "group": "drink",
    "link": ""
  },
  {
    "id": "itmeistee036",
    "name": "Peach",
    "originalName": "Eistee Pfirsich",
    "type": "item",
    "group": "drink",
    "link": ""
  },
  {
    "id": "itmapfels037",
    "name": "Apfelschorle",
    "originalName": "Apfelschorle",
    "type": "item",
    "group": "drink",
    "link": ""
  },
  {
    "id": "itmorange038",
    "name": "Orangensaft",
    "originalName": "Orangensaft",
    "type": "item",
    "group": "drink",
    "link": ""
  },
  {
    "id": "itmapfels039",
    "name": "Apfelsaft",
    "originalName": "Apfelsaft",
    "type": "item",
    "group": "drink",
    "link": ""
  },
  {
    "id": "itmtraube040",
    "name": "Traubensaft",
    "originalName": "Traubensaft",
    "type": "item",
    "group": "drink",
    "link": ""
  },
  {
    "id": "itmmultiv041",
    "name": "Multivitaminsaft",
    "originalName": "Multivitaminsaft",
    "type": "item",
    "group": "drink",
    "link": ""
  },
  {
    "id": "itmenergy042",
    "name": "Drink",
    "originalName": "Energy Drink",
    "type": "item",
    "group": "drink",
    "link": ""
  },
  {
    "id": "itmkaffee043",
    "name": "Kaffee",
    "originalName": "Kaffee",
    "type": "item",
    "group": "drink",
    "link": ""
  },
  {
    "id": "itmespres044",
    "name": "Espresso",
    "originalName": "Espresso",
    "type": "item",
    "group": "drink",
    "link": ""
  },
  {
    "id": "itmdoppel045",
    "name": "Espresso",
    "originalName": "Doppelter Espresso",
    "type": "item",
    "group": "drink",
    "link": ""
  },
  {
    "id": "itmcappuc046",
    "name": "Cappuccino",
    "originalName": "Cappuccino",
    "type": "item",
    "group": "drink",
    "link": ""
  },
  {
    "id": "itmlattem047",
    "name": "Macchiato",
    "originalName": "Latte Macchiato",
    "type": "item",
    "group": "drink",
    "link": ""
  },
  {
    "id": "itmmilchk048",
    "name": "Milchkaffee",
    "originalName": "Milchkaffee",
    "type": "item",
    "group": "drink",
    "link": ""
  },
  {
    "id": "itmkakaoh049",
    "name": "Schokolade",
    "originalName": "Kakao / Heiße Schokolade",
    "type": "item",
    "group": "drink",
    "link": ""
  },
  {
    "id": "itmteesch050",
    "name": "Schwarz",
    "originalName": "Tee Schwarz",
    "type": "item",
    "group": "drink",
    "link": ""
  },
  {
    "id": "itmteegru051",
    "name": "Grun",
    "originalName": "Tee Grün",
    "type": "item",
    "group": "drink",
    "link": ""
  },
  {
    "id": "itmkraute052",
    "name": "Krautertee",
    "originalName": "Kräutertee",
    "type": "item",
    "group": "drink",
    "link": ""
  },
  {
    "id": "itmpfeffe053",
    "name": "Pfefferminztee",
    "originalName": "Pfefferminztee",
    "type": "item",
    "group": "drink",
    "link": ""
  },
  {
    "id": "itmingwer054",
    "name": "Ingwertee",
    "originalName": "Ingwertee",
    "type": "item",
    "group": "drink",
    "link": ""
  },
  {
    "id": "itmalkoho055",
    "name": "Beer",
    "originalName": "Alkoholfreies Bier",
    "type": "item",
    "group": "drink",
    "link": ""
  },
  {
    "id": "itmmalzbi056",
    "name": "Beer",
    "originalName": "Malzbier",
    "type": "item",
    "group": "drink",
    "link": ""
  },
  {
    "id": "itmfrucht057",
    "name": "Schorlen",
    "originalName": "Früchte-Schorlen",
    "type": "item",
    "group": "drink",
    "link": ""
  },
  {
    "id": "itmhausge058",
    "name": "Lemonade",
    "originalName": "Hausgemachte Limonade",
    "type": "item",
    "group": "drink",
    "link": ""
  },
  {
    "id": "itmginger059",
    "name": "Ale",
    "originalName": "Ginger Ale",
    "type": "item",
    "group": "drink",
    "link": ""
  },
  {
    "id": "itmbitter060",
    "name": "Lemon",
    "originalName": "Bitter Lemon",
    "type": "item",
    "group": "drink",
    "link": ""
  },
  {
    "id": "itmtonicw061",
    "name": "Water",
    "originalName": "Tonic Water",
    "type": "item",
    "group": "drink",
    "link": ""
  },
  {
    "id": "itmpils062",
    "name": "Pilsner",
    "originalName": "Pils",
    "type": "item",
    "group": "drink",
    "link": ""
  },
  {
    "id": "itmhelles063",
    "name": "Lager",
    "originalName": "Helles",
    "type": "item",
    "group": "drink",
    "link": ""
  },
  {
    "id": "itmweibie064",
    "name": "Beer",
    "originalName": "Weißbier / Weizenbier",
    "type": "item",
    "group": "drink",
    "link": ""
  },
  {
    "id": "itmkolsch065",
    "name": "Kolsch",
    "originalName": "Kölsch",
    "type": "item",
    "group": "drink",
    "link": ""
  },
  {
    "id": "itmaltbie066",
    "name": "Altbier",
    "originalName": "Altbier",
    "type": "item",
    "group": "drink",
    "link": ""
  },
  {
    "id": "itmdunkle067",
    "name": "Beer",
    "originalName": "Dunkles Bier",
    "type": "item",
    "group": "drink",
    "link": ""
  },
  {
    "id": "itmbecks068",
    "name": "Becks",
    "originalName": "Beck’s",
    "type": "item",
    "group": "drink",
    "link": ""
  },
  {
    "id": "itmbitbur069",
    "name": "Bitburger",
    "originalName": "Bitburger",
    "type": "item",
    "group": "drink",
    "link": ""
  },
  {
    "id": "itmkromba070",
    "name": "Krombacher",
    "originalName": "Krombacher",
    "type": "item",
    "group": "drink",
    "link": ""
  },
  {
    "id": "itmerding071",
    "name": "Erdinger",
    "originalName": "Erdinger",
    "type": "item",
    "group": "drink",
    "link": ""
  },
  {
    "id": "itmpaulan072",
    "name": "Paulaner",
    "originalName": "Paulaner",
    "type": "item",
    "group": "drink",
    "link": ""
  },
  {
    "id": "itmjever073",
    "name": "Jever",
    "originalName": "Jever",
    "type": "item",
    "group": "drink",
    "link": ""
  },
  {
    "id": "itmoettin074",
    "name": "Oettinger",
    "originalName": "Oettinger",
    "type": "item",
    "group": "drink",
    "link": ""
  },
  {
    "id": "itmradler075",
    "name": "Shandy",
    "originalName": "Radler",
    "type": "item",
    "group": "drink",
    "link": ""
  },
  {
    "id": "itmdiesel076",
    "name": "Mix",
    "originalName": "Diesel",
    "type": "item",
    "group": "drink",
    "link": ""
  },
  {
    "id": "itmweizen077",
    "name": "Weizenbock",
    "originalName": "Weizenbock",
    "type": "item",
    "group": "drink",
    "link": ""
  },
  {
    "id": "itmschwar078",
    "name": "Beer",
    "originalName": "Schwarzbier",
    "type": "item",
    "group": "drink",
    "link": ""
  },
  {
    "id": "itmriesli079",
    "name": "Riesling",
    "originalName": "Riesling",
    "type": "item",
    "group": "drink",
    "link": ""
  },
  {
    "id": "itmgraubu080",
    "name": "Gris",
    "originalName": "Grauburgunder",
    "type": "item",
    "group": "drink",
    "link": ""
  },
  {
    "id": "itmweibur081",
    "name": "Weiburgunder",
    "originalName": "Weißburgunder",
    "type": "item",
    "group": "drink",
    "link": ""
  },
  {
    "id": "itmsilvan082",
    "name": "Silvaner",
    "originalName": "Silvaner",
    "type": "item",
    "group": "drink",
    "link": ""
  },
  {
    "id": "itmchardo083",
    "name": "Chardonnay",
    "originalName": "Chardonnay",
    "type": "item",
    "group": "drink",
    "link": ""
  },
  {
    "id": "itmspatbu084",
    "name": "Spatburgunder",
    "originalName": "Spätburgunder",
    "type": "item",
    "group": "drink",
    "link": ""
  },
  {
    "id": "itmdornfe085",
    "name": "Dornfelder",
    "originalName": "Dornfelder",
    "type": "item",
    "group": "drink",
    "link": ""
  },
  {
    "id": "itmmerlot086",
    "name": "Merlot",
    "originalName": "Merlot",
    "type": "item",
    "group": "drink",
    "link": ""
  },
  {
    "id": "itmcabern087",
    "name": "Sauvignon",
    "originalName": "Cabernet Sauvignon",
    "type": "item",
    "group": "drink",
    "link": ""
  },
  {
    "id": "itmrosecu088",
    "name": "Cuvee",
    "originalName": "Rosé Cuvée",
    "type": "item",
    "group": "drink",
    "link": ""
  },
  {
    "id": "itmsekt089",
    "name": "Sparkling",
    "originalName": "Sekt",
    "type": "item",
    "group": "drink",
    "link": ""
  },
  {
    "id": "itmprosec090",
    "name": "Prosecco",
    "originalName": "Prosecco",
    "type": "item",
    "group": "drink",
    "link": ""
  },
  {
    "id": "itmaperol091",
    "name": "Spritz",
    "originalName": "Aperol Spritz",
    "type": "item",
    "group": "drink",
    "link": ""
  },
  {
    "id": "itmhugo092",
    "name": "Hugo",
    "originalName": "Hugo",
    "type": "item",
    "group": "drink",
    "link": ""
  },
  {
    "id": "itmcampar093",
    "name": "Soda",
    "originalName": "Campari Soda",
    "type": "item",
    "group": "drink",
    "link": ""
  },
  {
    "id": "itmvodka094",
    "name": "Vodka",
    "originalName": "Vodka",
    "type": "item",
    "group": "drink",
    "link": ""
  },
  {
    "id": "itmrum095",
    "name": "Rum",
    "originalName": "Rum",
    "type": "item",
    "group": "drink",
    "link": ""
  },
  {
    "id": "itmgin096",
    "name": "Gin",
    "originalName": "Gin",
    "type": "item",
    "group": "drink",
    "link": ""
  },
  {
    "id": "itmwhiske097",
    "name": "Whiskey",
    "originalName": "Whiskey",
    "type": "item",
    "group": "drink",
    "link": ""
  },
  {
    "id": "itmtequil098",
    "name": "Tequila",
    "originalName": "Tequila",
    "type": "item",
    "group": "drink",
    "link": ""
  },
  {
    "id": "itmjagerm099",
    "name": "Jaegermeister",
    "originalName": "Jägermeister",
    "type": "item",
    "group": "drink",
    "link": ""
  },
  {
    "id": "itmobstle100",
    "name": "Schnapps",
    "originalName": "Obstler",
    "type": "item",
    "group": "drink",
    "link": ""
  },
  {
    "id": "itmmojito101",
    "name": "Mojito",
    "originalName": "Mojito",
    "type": "item",
    "group": "drink",
    "link": ""
  },
  {
    "id": "itmcaipir102",
    "name": "Caipirinha",
    "originalName": "Caipirinha",
    "type": "item",
    "group": "drink",
    "link": ""
  },
  {
    "id": "itmsexont103",
    "name": "Beach",
    "originalName": "Sex on the Beach",
    "type": "item",
    "group": "drink",
    "link": ""
  },
  {
    "id": "itmpinaco104",
    "name": "Colada",
    "originalName": "Piña Colada",
    "type": "item",
    "group": "drink",
    "link": ""
  },
  {
    "id": "itmginton105",
    "name": "Tonic",
    "originalName": "Gin Tonic",
    "type": "item",
    "group": "drink",
    "link": ""
  },
  {
    "id": "itmtequil106",
    "name": "Sunrise",
    "originalName": "Tequila Sunrise",
    "type": "item",
    "group": "drink",
    "link": ""
  },
  {
    "id": "itmmaitai107",
    "name": "Tai",
    "originalName": "Mai Tai",
    "type": "item",
    "group": "drink",
    "link": ""
  },
  {
    "id": "itmmargar108",
    "name": "Margarita",
    "originalName": "Margarita",
    "type": "item",
    "group": "drink",
    "link": ""
  },
  {
    "id": "itfbrusch109",
    "name": "Bruschetta",
    "originalName": "Bruschetta",
    "type": "item",
    "group": "food",
    "link": ""
  },
  {
    "id": "itfgarlic110",
    "name": "Bread",
    "originalName": "Garlic Bread",
    "type": "item",
    "group": "food",
    "link": ""
  },
  {
    "id": "itfmozzar111",
    "name": "Sticks",
    "originalName": "Mozzarella Sticks",
    "type": "item",
    "group": "food",
    "link": ""
  },
  {
    "id": "itfcapres112",
    "name": "Caprese",
    "originalName": "Caprese",
    "type": "item",
    "group": "food",
    "link": ""
  },
  {
    "id": "itfantipa113",
    "name": "Teller",
    "originalName": "Antipasti Teller",
    "type": "item",
    "group": "food",
    "link": ""
  },
  {
    "id": "itfonionr114",
    "name": "Rings",
    "originalName": "Onion Rings",
    "type": "item",
    "group": "food",
    "link": ""
  },
  {
    "id": "itfchicke115",
    "name": "Wings",
    "originalName": "Chicken Wings",
    "type": "item",
    "group": "food",
    "link": ""
  },
  {
    "id": "itfsupped116",
    "name": "Tages",
    "originalName": "Suppe des Tages",
    "type": "item",
    "group": "food",
    "link": ""
  },
  {
    "id": "itftomate117",
    "name": "Soup",
    "originalName": "Tomatensuppe",
    "type": "item",
    "group": "food",
    "link": ""
  },
  {
    "id": "itfkurbis118",
    "name": "Kurbissuppe",
    "originalName": "Kürbissuppe",
    "type": "item",
    "group": "food",
    "link": ""
  },
  {
    "id": "itfminest119",
    "name": "Minestrone",
    "originalName": "Minestrone",
    "type": "item",
    "group": "food",
    "link": ""
  },
  {
    "id": "itfcaesar120",
    "name": "Salad",
    "originalName": "Caesar Salad",
    "type": "item",
    "group": "food",
    "link": ""
  },
  {
    "id": "itfcaesar121",
    "name": "Salad",
    "originalName": "Caesar Chicken Salad",
    "type": "item",
    "group": "food",
    "link": ""
  },
  {
    "id": "itfgruner122",
    "name": "Salat",
    "originalName": "Grüner Salat",
    "type": "item",
    "group": "food",
    "link": ""
  },
  {
    "id": "itfgemisc123",
    "name": "Salat",
    "originalName": "Gemischter Salat",
    "type": "item",
    "group": "food",
    "link": ""
  },
  {
    "id": "itfthunfi124",
    "name": "Thunfischsalat",
    "originalName": "Thunfischsalat",
    "type": "item",
    "group": "food",
    "link": ""
  },
  {
    "id": "itfbauern125",
    "name": "Salad",
    "originalName": "Bauernsalat",
    "type": "item",
    "group": "food",
    "link": ""
  },
  {
    "id": "itfmozzar126",
    "name": "Salat",
    "originalName": "Mozzarella Salat",
    "type": "item",
    "group": "food",
    "link": ""
  },
  {
    "id": "itfavocad127",
    "name": "Salat",
    "originalName": "Avocado Salat",
    "type": "item",
    "group": "food",
    "link": ""
  },
  {
    "id": "itfpizzam128",
    "name": "Margherita",
    "originalName": "Pizza Margherita",
    "type": "item",
    "group": "food",
    "link": ""
  },
  {
    "id": "itfpizzas129",
    "name": "Salami",
    "originalName": "Pizza Salami",
    "type": "item",
    "group": "food",
    "link": ""
  },
  {
    "id": "itfpizzaf130",
    "name": "Mushroom",
    "originalName": "Pizza Funghi",
    "type": "item",
    "group": "food",
    "link": ""
  },
  {
    "id": "itfpizzat131",
    "name": "Tuna",
    "originalName": "Pizza Tonno",
    "type": "item",
    "group": "food",
    "link": ""
  },
  {
    "id": "itfpizzah132",
    "name": "Hawaiian",
    "originalName": "Pizza Hawaii",
    "type": "item",
    "group": "food",
    "link": ""
  },
  {
    "id": "itfpizzap133",
    "name": "Prosciutto",
    "originalName": "Pizza Prosciutto",
    "type": "item",
    "group": "food",
    "link": ""
  },
  {
    "id": "itfpizzav134",
    "name": "Vegetarian",
    "originalName": "Pizza Vegetarisch",
    "type": "item",
    "group": "food",
    "link": ""
  },
  {
    "id": "itfpizzaq135",
    "name": "Cheese",
    "originalName": "Pizza Quattro Formaggi",
    "type": "item",
    "group": "food",
    "link": ""
  },
  {
    "id": "itfpizzad136",
    "name": "Spicy",
    "originalName": "Pizza Diavolo",
    "type": "item",
    "group": "food",
    "link": ""
  },
  {
    "id": "itfpizzab137",
    "name": "Chicken",
    "originalName": "Pizza BBQ Chicken",
    "type": "item",
    "group": "food",
    "link": ""
  },
  {
    "id": "itfpizzap138",
    "name": "Pepperoni",
    "originalName": "Pizza Pepperoni",
    "type": "item",
    "group": "food",
    "link": ""
  },
  {
    "id": "itfspaghe139",
    "name": "Bolognese",
    "originalName": "Spaghetti Bolognese",
    "type": "item",
    "group": "food",
    "link": ""
  },
  {
    "id": "itfspaghe140",
    "name": "Carbonara",
    "originalName": "Spaghetti Carbonara",
    "type": "item",
    "group": "food",
    "link": ""
  },
  {
    "id": "itfpennea141",
    "name": "Arrabiata",
    "originalName": "Penne Arrabiata",
    "type": "item",
    "group": "food",
    "link": ""
  },
  {
    "id": "itflasagn142",
    "name": "Lasagne",
    "originalName": "Lasagne",
    "type": "item",
    "group": "food",
    "link": ""
  },
  {
    "id": "itffettuc143",
    "name": "Alfredo",
    "originalName": "Fettuccine Alfredo",
    "type": "item",
    "group": "food",
    "link": ""
  },
  {
    "id": "itftortel144",
    "name": "Cream",
    "originalName": "Tortellini Panna",
    "type": "item",
    "group": "food",
    "link": ""
  },
  {
    "id": "itfgnocch145",
    "name": "Tomatensoe",
    "originalName": "Gnocchi mit Tomatensoße",
    "type": "item",
    "group": "food",
    "link": ""
  },
  {
    "id": "itftaglia146",
    "name": "Salmon",
    "originalName": "Tagliatelle Lachs",
    "type": "item",
    "group": "food",
    "link": ""
  },
  {
    "id": "itfpennep147",
    "name": "Pesto",
    "originalName": "Penne Pesto",
    "type": "item",
    "group": "food",
    "link": ""
  },
  {
    "id": "itfschnit148",
    "name": "Art",
    "originalName": "Schnitzel Wiener Art",
    "type": "item",
    "group": "food",
    "link": ""
  },
  {
    "id": "itfjagers149",
    "name": "Jagerschnitzel",
    "originalName": "Jägerschnitzel",
    "type": "item",
    "group": "food",
    "link": ""
  },
  {
    "id": "itfzigeun150",
    "name": "Zigeunerschnitzel",
    "originalName": "Zigeunerschnitzel",
    "type": "item",
    "group": "food",
    "link": ""
  },
  {
    "id": "itfrinder151",
    "name": "Rindersteak",
    "originalName": "Rindersteak",
    "type": "item",
    "group": "food",
    "link": ""
  },
  {
    "id": "itfhahnch152",
    "name": "Hahnchenbrustfilet",
    "originalName": "Hähnchenbrustfilet",
    "type": "item",
    "group": "food",
    "link": ""
  },
  {
    "id": "itfschwei153",
    "name": "Schweinesteak",
    "originalName": "Schweinesteak",
    "type": "item",
    "group": "food",
    "link": ""
  },
  {
    "id": "itfbratwu154",
    "name": "Sausage",
    "originalName": "Bratwurst",
    "type": "item",
    "group": "food",
    "link": ""
  },
  {
    "id": "itfcurryw155",
    "name": "Sausage",
    "originalName": "Currywurst",
    "type": "item",
    "group": "food",
    "link": ""
  },
  {
    "id": "itfbeefbu156",
    "name": "Burger",
    "originalName": "Beef Burger",
    "type": "item",
    "group": "food",
    "link": ""
  },
  {
    "id": "itfchicke157",
    "name": "Burger",
    "originalName": "Chicken Burger",
    "type": "item",
    "group": "food",
    "link": ""
  },
  {
    "id": "itfcheese158",
    "name": "Cheeseburger",
    "originalName": "Cheeseburger",
    "type": "item",
    "group": "food",
    "link": ""
  },
  {
    "id": "itflachsf159",
    "name": "Lachsfilet",
    "originalName": "Lachsfilet",
    "type": "item",
    "group": "food",
    "link": ""
  },
  {
    "id": "itffishch160",
    "name": "Chips",
    "originalName": "Fish & Chips",
    "type": "item",
    "group": "food",
    "link": ""
  },
  {
    "id": "itfgebrat161",
    "name": "Zander",
    "originalName": "Gebratener Zander",
    "type": "item",
    "group": "food",
    "link": ""
  },
  {
    "id": "itfgarnel162",
    "name": "Garnelenpfanne",
    "originalName": "Garnelenpfanne",
    "type": "item",
    "group": "food",
    "link": ""
  },
  {
    "id": "itfcalama163",
    "name": "Calamari",
    "originalName": "Calamari",
    "type": "item",
    "group": "food",
    "link": ""
  },
  {
    "id": "itfveggie164",
    "name": "Burger",
    "originalName": "Veggie Burger",
    "type": "item",
    "group": "food",
    "link": ""
  },
  {
    "id": "itffalafe165",
    "name": "Teller",
    "originalName": "Falafel Teller",
    "type": "item",
    "group": "food",
    "link": ""
  },
  {
    "id": "itfgemuse166",
    "name": "Gemusepfanne",
    "originalName": "Gemüsepfanne",
    "type": "item",
    "group": "food",
    "link": ""
  },
  {
    "id": "itfveggie167",
    "name": "Pasta",
    "originalName": "Veggie Pasta",
    "type": "item",
    "group": "food",
    "link": ""
  },
  {
    "id": "itfveggie168",
    "name": "Pizza",
    "originalName": "Veggie Pizza",
    "type": "item",
    "group": "food",
    "link": ""
  },
  {
    "id": "itfkasesp169",
    "name": "Kasespatzle",
    "originalName": "Käsespätzle",
    "type": "item",
    "group": "food",
    "link": ""
  },
  {
    "id": "itfkartof170",
    "name": "Kartoffelpuffer",
    "originalName": "Kartoffelpuffer",
    "type": "item",
    "group": "food",
    "link": ""
  },
  {
    "id": "itfveganb171",
    "name": "Bowl",
    "originalName": "Vegan Bowl",
    "type": "item",
    "group": "food",
    "link": ""
  },
  {
    "id": "itfvegane172",
    "name": "Curry",
    "originalName": "Veganes Curry",
    "type": "item",
    "group": "food",
    "link": ""
  },
  {
    "id": "itfvegane173",
    "name": "Pasta",
    "originalName": "Vegane Pasta",
    "type": "item",
    "group": "food",
    "link": ""
  },
  {
    "id": "itfvegane174",
    "name": "Schnitzel",
    "originalName": "Veganes Schnitzel",
    "type": "item",
    "group": "food",
    "link": ""
  },
  {
    "id": "itfvegane175",
    "name": "Chili",
    "originalName": "Veganes Chili",
    "type": "item",
    "group": "food",
    "link": ""
  },
  {
    "id": "itfpommes176",
    "name": "Frites",
    "originalName": "Pommes Frites",
    "type": "item",
    "group": "food",
    "link": ""
  },
  {
    "id": "itfsukart177",
    "name": "Fries",
    "originalName": "Süßkartoffel Pommes",
    "type": "item",
    "group": "food",
    "link": ""
  },
  {
    "id": "itfkartof178",
    "name": "Kartoffelsalat",
    "originalName": "Kartoffelsalat",
    "type": "item",
    "group": "food",
    "link": ""
  },
  {
    "id": "itfbratka179",
    "name": "Potatoes",
    "originalName": "Bratkartoffeln",
    "type": "item",
    "group": "food",
    "link": ""
  },
  {
    "id": "itfreis180",
    "name": "Reis",
    "originalName": "Reis",
    "type": "item",
    "group": "food",
    "link": ""
  },
  {
    "id": "itfkartof181",
    "name": "Kartoffelknodel",
    "originalName": "Kartoffelknödel",
    "type": "item",
    "group": "food",
    "link": ""
  },
  {
    "id": "itfgemuse182",
    "name": "Vegetable",
    "originalName": "Gemüse",
    "type": "item",
    "group": "food",
    "link": ""
  },
  {
    "id": "itftirami183",
    "name": "Tiramisu",
    "originalName": "Tiramisu",
    "type": "item",
    "group": "food",
    "link": ""
  },
  {
    "id": "itfschoko184",
    "name": "Warm",
    "originalName": "Schokokuchen (warm)",
    "type": "item",
    "group": "food",
    "link": ""
  },
  {
    "id": "itfapfels185",
    "name": "Apfelstrudel",
    "originalName": "Apfelstrudel",
    "type": "item",
    "group": "food",
    "link": ""
  },
  {
    "id": "itfkaseku186",
    "name": "Kasekuchen",
    "originalName": "Käsekuchen",
    "type": "item",
    "group": "food",
    "link": ""
  },
  {
    "id": "itfpannac187",
    "name": "Cotta",
    "originalName": "Panna Cotta",
    "type": "item",
    "group": "food",
    "link": ""
  },
  {
    "id": "itfeisaus188",
    "name": "Auswahl",
    "originalName": "Eis Auswahl",
    "type": "item",
    "group": "food",
    "link": ""
  },
  {
    "id": "itfwaffel189",
    "name": "Cream",
    "originalName": "Waffeln mit Eis",
    "type": "item",
    "group": "food",
    "link": ""
  },
  {
    "id": "itfkinder190",
    "name": "Pizza",
    "originalName": "Kinder-Pizza",
    "type": "item",
    "group": "food",
    "link": ""
  },
  {
    "id": "itfchicke191",
    "name": "Fries",
    "originalName": "Chicken Nuggets + Pommes",
    "type": "item",
    "group": "food",
    "link": ""
  },
  {
    "id": "itfminisc192",
    "name": "Schnitzel",
    "originalName": "Mini-Schnitzel",
    "type": "item",
    "group": "food",
    "link": ""
  },
  {
    "id": "itfpastam193",
    "name": "Tomatensoe",
    "originalName": "Pasta mit Tomatensoße",
    "type": "item",
    "group": "food",
    "link": ""
  },
  {
    "id": "itfminibu194",
    "name": "Burger",
    "originalName": "Mini-Burger",
    "type": "item",
    "group": "food",
    "link": ""
  },
  {
    "id": "itobrusch195",
    "name": "Bruschetta",
    "originalName": "Bruschetta",
    "type": "item",
    "group": "other",
    "link": ""
  },
  {
    "id": "itogarlic196",
    "name": "Bread",
    "originalName": "Garlic Bread",
    "type": "item",
    "group": "other",
    "link": ""
  },
  {
    "id": "itomozzar197",
    "name": "Sticks",
    "originalName": "Mozzarella Sticks",
    "type": "item",
    "group": "other",
    "link": ""
  },
  {
    "id": "itocapres198",
    "name": "Caprese",
    "originalName": "Caprese",
    "type": "item",
    "group": "other",
    "link": ""
  },
  {
    "id": "itoantipa199",
    "name": "Teller",
    "originalName": "Antipasti Teller",
    "type": "item",
    "group": "other",
    "link": ""
  },
  {
    "id": "itoonionr200",
    "name": "Rings",
    "originalName": "Onion Rings",
    "type": "item",
    "group": "other",
    "link": ""
  },
  {
    "id": "itochicke201",
    "name": "Wings",
    "originalName": "Chicken Wings",
    "type": "item",
    "group": "other",
    "link": ""
  },
  {
    "id": "itosupped202",
    "name": "Tages",
    "originalName": "Suppe des Tages",
    "type": "item",
    "group": "other",
    "link": ""
  },
  {
    "id": "itotomate203",
    "name": "Soup",
    "originalName": "Tomatensuppe",
    "type": "item",
    "group": "other",
    "link": ""
  },
  {
    "id": "itokurbis204",
    "name": "Kurbissuppe",
    "originalName": "Kürbissuppe",
    "type": "item",
    "group": "other",
    "link": ""
  },
  {
    "id": "itominest205",
    "name": "Minestrone",
    "originalName": "Minestrone",
    "type": "item",
    "group": "other",
    "link": ""
  },
  {
    "id": "itotirami206",
    "name": "Tiramisu",
    "originalName": "Tiramisu",
    "type": "item",
    "group": "other",
    "link": ""
  },
  {
    "id": "itoschoko207",
    "name": "Warm",
    "originalName": "Schokokuchen (warm)",
    "type": "item",
    "group": "other",
    "link": ""
  },
  {
    "id": "itoapfels208",
    "name": "Apfelstrudel",
    "originalName": "Apfelstrudel",
    "type": "item",
    "group": "other",
    "link": ""
  },
  {
    "id": "itokaseku209",
    "name": "Kasekuchen",
    "originalName": "Käsekuchen",
    "type": "item",
    "group": "other",
    "link": ""
  },
  {
    "id": "itopannac210",
    "name": "Cotta",
    "originalName": "Panna Cotta",
    "type": "item",
    "group": "other",
    "link": ""
  },
  {
    "id": "itoeisaus211",
    "name": "Auswahl",
    "originalName": "Eis Auswahl",
    "type": "item",
    "group": "other",
    "link": ""
  },
  {
    "id": "itowaffel212",
    "name": "Cream",
    "originalName": "Waffeln mit Eis",
    "type": "item",
    "group": "other",
    "link": ""
  },
  {
    "id": "itocremeb213",
    "name": "Brulee",
    "originalName": "Crème Brûlée",
    "type": "item",
    "group": "other",
    "link": ""
  },
  {
    "id": "itoobstsa214",
    "name": "Salad",
    "originalName": "Obstsalat",
    "type": "item",
    "group": "other",
    "link": ""
  }
]